galsynthspec/__init__.py
galsynthspec/paths.py
galsynthspec/cli/wrappers.py
galsynthspec/datamodels/__init__.py
galsynthspec/datamodels/fitresult.py
galsynthspec/datamodels/galaxy.py
galsynthspec/datamodels/photometry.py
galsynthspec/download/__init__.py
galsynthspec/download/all.py
galsynthspec/download/galex.py
galsynthspec/download/ps1.py
galsynthspec/download/sdss.py
galsynthspec/download/twomass.py
galsynthspec/download/wise.py
galsynthspec/model/__init__.py
galsynthspec/model/configure.py
galsynthspec/model/sps.py
galsynthspec/plotting/__init__.py
galsynthspec/plotting/corner.py
galsynthspec/plotting/sed.py
galsynthspec/run/__init__.py
galsynthspec/run/analyse.py
galsynthspec/run/fit.py
galsynthspec/run/run.py
galsynthspec/skyportal/__init__.py
galsynthspec/skyportal/base_client.py
galsynthspec/skyportal/query.py
galsynthspec/utils/__init__.py
galsynthspec/utils/extinction.py
galsynthspec/utils/predict.py
galsynthspec/utils/query.py
galsynthspec/utils/tns.py
galsynthspec-0.2.1.dist-info/licenses/LICENSE
galsynthspec-0.2.1.dist-info/METADATA
galsynthspec-0.2.1.dist-info/WHEEL
galsynthspec-0.2.1.dist-info/entry_points.txt
galsynthspec-0.2.1.dist-info/top_level.txt
galsynthspec-0.2.1.dist-info/RECORD
