Metadata-Version: 2.4
Name: galsynthspec
Version: 0.2.1
Summary: Synthesize galaxy spectra from photometry
Author-email: Robert Stein <rdstein@caltech.edu>
License: MIT
Project-URL: Homepage, https://github.com/robertdstein/galsynthspec
Requires-Python: >=3.10
License-File: LICENSE
Requires-Dist: jupyter
Requires-Dist: matplotlib
Requires-Dist: astropy
Requires-Dist: matplotlib
Requires-Dist: numpy<2.0.0
Requires-Dist: pandas
Requires-Dist: astroquery
Requires-Dist: astro-prospector<2.0.0
Requires-Dist: fsps
Requires-Dist: dynesty
Requires-Dist: astro-sedpy
Requires-Dist: h5py
Requires-Dist: corner
Requires-Dist: scipy
Requires-Dist: dynesty
Requires-Dist: sedpy
Requires-Dist: pydantic>=2.0.0
Requires-Dist: numpydantic
Requires-Dist: python-dotenv
Requires-Dist: click
Requires-Dist: tqdm
Requires-Dist: sfdmap2
Requires-Dist: extinction
Provides-Extra: dev
Requires-Dist: black==25.1.0; extra == "dev"
Requires-Dist: isort==6.0.1; extra == "dev"
Requires-Dist: pylint==3.3.7; extra == "dev"
Requires-Dist: coveralls; extra == "dev"
Requires-Dist: pre-commit; extra == "dev"
Dynamic: license-file
